nativecap.so
nativecap-1.0.3.dist-info/top_level.txt
nativecap-1.0.3.dist-info/RECORD
nativecap-1.0.3.dist-info/METADATA
nativecap-1.0.3.dist-info/LICENSE
nativecap-1.0.3.dist-info/WHEEL
nativecap/__init__.py
