Metadata-Version: 2.1
Name: nativecap
Version: 1.0.3
Summary: Native screen capture module
Home-page: https://github.com/aisouard/pynativecap
Author: Axel Isouard
Author-email: axel@isouard.fr
License: MIT
Platform: UNKNOWN
Classifier: Development Status :: 3 - Alpha
Classifier: License :: OSI Approved :: MIT License
Classifier: Programming Language :: Python
Classifier: Programming Language :: Python :: 2.7
Classifier: Programming Language :: Python :: 3.5
Classifier: Programming Language :: Python :: 3.6
Classifier: Programming Language :: Python :: 3.7
Classifier: Programming Language :: Python :: 3.8
